[
    {
        "id": "wget",
        "ty": "suspicious",
        "constant_matchers": [
            "wget"
        ],
        "score": 20
    },
    {
        "id": "curl",
        "ty": "suspicious",
        "constant_matchers": [
            "curl.exe"
        ],
        "os": "windows",
        "score": 30
    },
    {
        "id": "discord_webhook",
        "ty": "malware_pattern",
        "constant_matchers": [
            "discord.com/api/webhooks",
            "DiscordWebhook"
        ],
        "score": 85
    },
    {
        "id": "pastebin",
        "ty": "suspicious",
        "constant_matchers": [
            "pastebin.com"
        ],
        "score": 15
    },
    {
        "id": "random_file_upload",
        "ty": "suspicious",
        "constant_matchers": [
            "anonfiles"
        ],
        "score": 45
    },
    {
        "id": "telegram",
        "ty": "smell",
        "constant_matchers": [
            "telegram"
        ],
        "score": 10
    },
    {
        "id": "onion_url",
        "ty": "suspicious",
        "constant_matchers": [
            ".onion"
        ],
        "score": 30
    },
    {
        "id": "post_request",
        "ty": "smell",
        "constant_matchers": [
            "POST"
        ],
        "score": 3
    },
    {
        "id": "http_connection",
        "ty": "smell",
        "constant_matchers": [
            "HttpURLConnection"
        ],
        "score": 3
    },
    {
        "id": "local_ip",
        "ty": "suspicious",
        "constant_matchers": [
            "127.0.0.1",
            "192.168"
        ],
        "score": 25
    }
]